rslearn/__init__.py
rslearn/arg_parser.py
rslearn/const.py
rslearn/lightning_cli.py
rslearn/log_utils.py
rslearn/main.py
rslearn/py.typed
rslearn/template_params.py
rslearn/config/__init__.py
rslearn/config/dataset.py
rslearn/data_sources/__init__.py
rslearn/data_sources/aws_landsat.py
rslearn/data_sources/aws_open_data.py
rslearn/data_sources/aws_sentinel1.py
rslearn/data_sources/climate_data_store.py
rslearn/data_sources/copernicus.py
rslearn/data_sources/data_source.py
rslearn/data_sources/earthdaily.py
rslearn/data_sources/earthdata_srtm.py
rslearn/data_sources/eurocrops.py
rslearn/data_sources/gcp_public_data.py
rslearn/data_sources/google_earth_engine.py
rslearn/data_sources/local_files.py
rslearn/data_sources/openstreetmap.py
rslearn/data_sources/planet.py
rslearn/data_sources/planet_basemap.py
rslearn/data_sources/planetary_computer.py
rslearn/data_sources/usda_cdl.py
rslearn/data_sources/usgs_landsat.py
rslearn/data_sources/utils.py
rslearn/data_sources/vector_source.py
rslearn/data_sources/worldcereal.py
rslearn/data_sources/worldcover.py
rslearn/data_sources/worldpop.py
rslearn/data_sources/xyz_tiles.py
rslearn/dataset/__init__.py
rslearn/dataset/add_windows.py
rslearn/dataset/dataset.py
rslearn/dataset/handler_summaries.py
rslearn/dataset/manage.py
rslearn/dataset/materialize.py
rslearn/dataset/remap.py
rslearn/dataset/window.py
rslearn/dataset/storage/__init__.py
rslearn/dataset/storage/file.py
rslearn/dataset/storage/storage.py
rslearn/models/__init__.py
rslearn/models/anysat.py
rslearn/models/attention_pooling.py
rslearn/models/clip.py
rslearn/models/component.py
rslearn/models/concatenate_features.py
rslearn/models/conv.py
rslearn/models/croma.py
rslearn/models/dinov3.py
rslearn/models/faster_rcnn.py
rslearn/models/feature_center_crop.py
rslearn/models/fpn.py
rslearn/models/module_wrapper.py
rslearn/models/molmo.py
rslearn/models/multitask.py
rslearn/models/panopticon.py
rslearn/models/pick_features.py
rslearn/models/pooling_decoder.py
rslearn-0.0.21.dist-info/licenses/LICENSE
rslearn-0.0.21.dist-info/licenses/NOTICE
rslearn-0.0.21.dist-info/METADATA
rslearn-0.0.21.dist-info/WHEEL
rslearn-0.0.21.dist-info/entry_points.txt
rslearn-0.0.21.dist-info/top_level.txt
rslearn-0.0.21.dist-info/RECORD
