Metadata-Version: 2.4
Name: rslearn
Version: 0.0.21
Summary: A library for developing remote sensing datasets and models
Author: OlmoEarth Team
License:                                  Apache License
Project-URL: homepage, https://github.com/allenai/rslearn
Project-URL: issues, https://github.com/allenai/rslearn/issues
Project-URL: repository, https://github.com/allenai/rslearn
Requires-Python: >=3.11
License-File: LICENSE
License-File: NOTICE
Requires-Dist: boto3>=1.39
Requires-Dist: fiona>=1.10
Requires-Dist: fsspec>=2025.10.0
Requires-Dist: jsonargparse>=4.35.0
Requires-Dist: lightning>=2.5.1.post0
Requires-Dist: Pillow>=11.3
Requires-Dist: pyproj>=3.7
Requires-Dist: python-dateutil>=2.9
Requires-Dist: pytimeparse>=1.1
Requires-Dist: rasterio>=1.4
Requires-Dist: shapely>=2.1
Requires-Dist: torch>=2.7.0
Requires-Dist: torchvision>=0.22.0
Requires-Dist: tqdm>=4.67
Requires-Dist: universal_pathlib>=0.2.6
Provides-Extra: extra
Requires-Dist: accelerate>=1.10; extra == "extra"
Requires-Dist: cdsapi>=0.7.6; extra == "extra"
Requires-Dist: earthdaily[platform]>=1.0.7; extra == "extra"
Requires-Dist: earthengine-api>=1.6.3; extra == "extra"
Requires-Dist: einops>=0.8; extra == "extra"
Requires-Dist: fsspec[gcs,s3]; extra == "extra"
Requires-Dist: google-cloud-bigquery>=3.35; extra == "extra"
Requires-Dist: google-cloud-storage>=2.18; extra == "extra"
Requires-Dist: huggingface_hub>=0.34.4; extra == "extra"
Requires-Dist: netCDF4>=1.7.2; extra == "extra"
Requires-Dist: osmium>=4.0.2; extra == "extra"
Requires-Dist: planet>=3.1; extra == "extra"
Requires-Dist: planetary_computer>=1.0; extra == "extra"
Requires-Dist: pycocotools>=2.0; extra == "extra"
Requires-Dist: pystac_client>=0.9; extra == "extra"
Requires-Dist: rtree>=1.4; extra == "extra"
Requires-Dist: termcolor>=3.0; extra == "extra"
Requires-Dist: satlaspretrain_models>=0.3; extra == "extra"
Requires-Dist: scipy>=1.16; extra == "extra"
Requires-Dist: terratorch>=1.0.2; extra == "extra"
Requires-Dist: transformers>=4.55; extra == "extra"
Requires-Dist: wandb>=0.21; extra == "extra"
Requires-Dist: timm>=0.9.7; extra == "extra"
Provides-Extra: dev
Requires-Dist: interrogate>=1.7.0; extra == "dev"
Requires-Dist: mypy<2,>=1.17.1; extra == "dev"
Requires-Dist: pre-commit>=4.3.0; extra == "dev"
Requires-Dist: pytest>=8.0; extra == "dev"
Requires-Dist: pytest_httpserver; extra == "dev"
Requires-Dist: ruff>=0.12.9; extra == "dev"
Requires-Dist: pytest-dotenv; extra == "dev"
Requires-Dist: pytest-xdist; extra == "dev"
Dynamic: license-file
